{
  "data": [
    {
      "id": 41,
      "attributes": {
        "created_at": "2022-10-16T13:54:17.000Z",
        "text": "RT @AI_Advice: The Ultimate List of #DataScience Skills\n\n#5G #100DaysOfCode #AI #Analytics #ArtificialIntelligence #BigData #Cloud #Data #I…",
        "edit_history_tweet_ids": [
          "1581644702058967040"
        ],
        "subject": "opensource"
      }
    },
    {
      "id": 42,
      "attributes": {
        "created_at": "2022-10-16T13:54:17.000Z",
        "text": "RT @AI_Advice: #AI/ #DataScience/ #MachineLearning:\nFREE #Infographic on Deep Learning Use Cases\n\n#5G #100DaysOfCode #Analytics #Artificial…",
        "edit_history_tweet_ids": [
          "1581644702046035968"
        ],
        "subject": "opensource"
      }
    },
    {
      "id": 43,
      "attributes": {
        "created_at": "2022-10-16T13:54:17.000Z",
        "text": "RT @AI_Advice: #AI/ #DataScience/ #MachineLearning:\nFREE #Infographic on Deep Learning Use Cases\n\n#5G #100DaysOfCode #Analytics #Artificial…",
        "edit_history_tweet_ids": [
          "1581644702042161159"
        ],
        "subject": "opensource"
      }
    },
    {
      "id": 44,
      "attributes": {
        "created_at": "2022-10-16T13:54:17.000Z",
        "text": "RT @AI_Advice: #MachineLearning Takes Hold in Nuclear Physics\n\nhttps://t.co/ZklenvyZBH\n\n#5G #100DaysOfCode #AI #Analytics #ArtificialIntell…",
        "edit_history_tweet_ids": [
          "1581644701996052480"
        ],
        "subject": "opensource"
      }
    },
    {
      "id": 45,
      "attributes": {
        "created_at": "2022-10-16T13:54:16.000Z",
        "text": "RT @AI_Advice: #AI/ #DataScience/ #MachineLearning:\nFREE #Infographic on Deep Learning Use Cases\n\n#5G #100DaysOfCode #Analytics #Artificial…",
        "edit_history_tweet_ids": [
          "1581644699362013184"
        ],
        "subject": "opensource"
      }
    },
    {
      "id": 46,
      "attributes": {
        "created_at": "2022-10-16T13:54:09.000Z",
        "text": "RT @ManavGambhir11: An amazing session to attend.Learnt about whatnot, from opensource to web3, I got to know about all. An amazing opportu…",
        "edit_history_tweet_ids": [
          "1581644671721566209"
        ],
        "subject": "opensource"
      }
    },
    {
      "id": 47,
      "attributes": {
        "created_at": "2022-10-16T13:54:01.000Z",
        "text": "RT @AI_Advice: #AI/ #DataScience/ #MachineLearning:\nFREE #Infographic on Deep Learning Use Cases\n\n#5G #100DaysOfCode #Analytics #Artificial…",
        "edit_history_tweet_ids": [
          "1581644635189182465"
        ],
        "subject": "opensource"
      }
    },
    {
      "id": 48,
      "attributes": {
        "created_at": "2022-10-16T13:53:59.000Z",
        "text": "RT @AI_Advice: The Ultimate List of #DataScience Skills\n\n#5G #100DaysOfCode #AI #Analytics #ArtificialIntelligence #BigData #Cloud #Data #I…",
        "edit_history_tweet_ids": [
          "1581644627203227649"
        ],
        "subject": "opensource"
      }
    },
    {
      "id": 49,
      "attributes": {
        "created_at": "2022-10-16T13:53:58.000Z",
        "text": "RT @Khushi1950: What I'm taking away from #hackthisfallhacktoberfest meet-up today?\n\n\"Come for swags, stay for the community❤️\"\n\nIt's a rea…",
        "edit_history_tweet_ids": [
          "1581644623562567681"
        ],
        "subject": "opensource"
      }
    },
    {
      "id": 50,
      "attributes": {
        "created_at": "2022-10-16T13:53:56.000Z",
        "text": "RT @AI_Advice: #AI/ #DataScience/ #MachineLearning:\nFREE #Infographic on Deep Learning Use Cases\n\n#5G #100DaysOfCode #Analytics #Artificial…",
        "edit_history_tweet_ids": [
          "1581644613609082882"
        ],
        "subject": "opensource"
      }
    }
  ]
}